soyuz/__init__.py
soyuz/configuration.py
soyuz/entrypoint.py
soyuz/heartbeat.py
soyuz/utils.py
soyuz/watchdog.py
soyuz/api/__init__.py
soyuz/api/dx.py
soyuz/api/exodus.py
soyuz/constellation/__init__.py
soyuz/constellation/api.py
soyuz/constellation/job_manager.py
soyuz/data/__init__.py
soyuz/data/daemons.py
soyuz/data/files.py
soyuz/data/folders.py
soyuz/data/records.py
soyuz/data/storages.py
soyuz/dx/__init__.py
soyuz/dx/context.py
soyuz/dx/sentinels.py
soyuz/dx/uploaders.py
soyuz/dx/variables.py
soyuz/event/__init__.py
soyuz/event/upload.py
natera_data_uploader-1.0.34.1.dist-info/LICENSE.txt
natera_data_uploader-1.0.34.1.dist-info/METADATA
natera_data_uploader-1.0.34.1.dist-info/WHEEL
natera_data_uploader-1.0.34.1.dist-info/entry_points.txt
natera_data_uploader-1.0.34.1.dist-info/top_level.txt
natera_data_uploader-1.0.34.1.dist-info/RECORD
