Metadata-Version: 2.1
Name: natera-data-uploader
Version: 1.0.34.1
Summary: Natera Uploader
Author: Nikita Berezin
Author-email: nberezin@natera.com
License: UNKNOWN
Platform: UNKNOWN
Classifier: Programming Language :: Python :: 2
Requires-Python: >=2.7
License-File: LICENSE.txt
Requires-Dist: dxpy (==0.318.1)
Requires-Dist: PyJWT (==1.7.1)
Requires-Dist: zope.event (==4.5.0)
